Workbook

Sheet DATA
B1: ID | C1: Title | D1: Year | E1: Age | F1: Rotten Tomatoes | G1: Netflix | H1: Hulu | I1: Prime Video | J1: Disney+ | K1: Type | L1: RT Score | M1: Platform Count
A2: 0 | B2: 1 | C2: The Irishman | D2: 2019 | E2: 18+ | F2: 98/100 | G2: 1 | H2: 0 | I2: 0 | J2: 0 | K2: 0 | L2: =IFERROR(VALUE(LEFT(F2,FIND("/",F2)-1))/10,"") -> 9.8 | M2: =SUM(G2:J2) -> 1
A3: 1 | B3: 2 | C3: Dangal | D3: 2016 | E3: 7+ | F3: 97/100 | G3: 1 | H3: 0 | I3: 0 | J3: 0 | K3: 0 | L3: =IFERROR(VALUE(LEFT(F3,FIND("/",F3)-1))/10,"") -> 9.7 | M3: =SUM(G3:J3) -> 1
A4: 2 | B4: 3 | C4: David Attenborough: A Life on Our Planet | D4: 2020 | E4: 7+ | F4: 95/100 | G4: 1 | H4: 0 | I4: 0 | J4: 0 | K4: 0 | L4: =IFERROR(VALUE(LEFT(F4,FIND("/",F4)-1))/10,"") -> 9.5 | M4: =SUM(G4:J4) -> 1
A5: 3 | B5: 4 | C5: Lagaan: Once Upon a Time in India | D5: 2001 | E5: 7+ | F5: 94/100 | G5: 1 | H5: 0 | I5: 0 | J5: 0 | K5: 0 | L5: =IFERROR(VALUE(LEFT(F5,FIND("/",F5)-1))/10,"") -> 9.4 | M5: =SUM(G5:J5) -> 1
A6: 4 | B6: 5 | C6: Roma | D6: 2018 | E6: 18+ | F6: 94/100 | G6: 1 | H6: 0 | I6: 0 | J6: 0 | K6: 0 | L6: =IFERROR(VALUE(LEFT(F6,FIND("/",F6)-1))/10,"") -> 9.4 | M6: =SUM(G6:J6) -> 1
A7: 5 | B7: 6 | C7: To All the Boys I've Loved Before | D7: 2018 | E7: 13+ | F7: 94/100 | G7: 1 | H7: 0 | I7: 0 | J7: 0 | K7: 0 | L7: =IFERROR(VALUE(LEFT(F7,FIND("/",F7)-1))/10,"") -> 9.4 | M7: =SUM(G7:J7) -> 1
A8: 6 | B8: 7 | C8: The Social Dilemma | D8: 2020 | E8: 13+ | F8: 93/100 | G8: 1 | H8: 0 | I8: 0 | J8: 0 | K8: 0 | L8: =IFERROR(VALUE(LEFT(F8,FIND("/",F8)-1))/10,"") -> 9.3 | M8: =SUM(G8:J8) -> 1
A9: 7 | B9: 8 | C9: Okja | D9: 2017 | E9: 13+ | F9: 92/100 | G9: 1 | H9: 0 | I9: 0 | J9: 0 | K9: 0 | L9: =IFERROR(VALUE(LEFT(F9,FIND("/",F9)-1))/10,"") -> 9.2 | M9: =SUM(G9:J9) -> 1
A10: 8 | B10: 9 | C10: The Ballad of Buster Scruggs | D10: 2018 | E10: 16+ | F10: 92/100 | G10: 1 | H10: 0 | I10: 0 | J10: 0 | K10: 0 | L10: =IFERROR(VALUE(LEFT(F10,FIND("/",F10)-1))/10,"") -> 9.2 | M10: =SUM(G10:J10) -> 1
A11: 9 | B11: 10 | C11: The Trial of the Chicago 7 | D11: 2020 | E11: 18+ | F11: 92/100 | G11: 1 | H11: 0 | I11: 0 | J11: 0 | K11: 0 | L11: =IFERROR(VALUE(LEFT(F11,FIND("/",F11)-1))/10,"") -> 9.2 | M11: =SUM(G11:J11) -> 1
A12: 10 | B12: 11 | C12: Article 15 | D12: 2019 | E12: 18+ | F12: 92/100 | G12: 1 | H12: 0 | I12: 0 | J12: 0 | K12: 0 | L12: =IFERROR(VALUE(LEFT(F12,FIND("/",F12)-1))/10,"") -> 9.2 | M12: =SUM(G12:J12) -> 1
A13: 11 | B13: 12 | C13: Jim & Andy: The Great Beyond- Featuring a Very Special, Contractually Obligated Mention of Tony Clifton | D13: 2017 | E13: 18+ | F13: 92/100 | G13: 1 | H13: 0 | I13: 0 | J13: 0 | K13: 0 | L13: =IFERROR(VALUE(LEFT(F13,FIND("/",F13)-1))/10,"") -> 9.2 | M13: =SUM(G13:J13) -> 1
... A36: 34 | B36: 35 | C36: Gerald's Game | D36: 2017 | E36: 18+ | F36: 88/100 | G36: 1 | H36: 0 | I36: 0 | J36: 0 | K36: 0 | L36: =IFERROR(VALUE(LEFT(F36,FIND("/",F36)-1))/10,"") -> 8.8 | M36: =SUM(G36:J36) -> 1
A37: 35 | B37: 36 | C37: On Body and Soul | D37: 2017 | F37: 88/100 | G37: 1 | H37: 0 | I37: 0 | J37: 0 | K37: 0 | L37: =IFERROR(VALUE(LEFT(F37,FIND("/",F37)-1))/10,"") -> 8.8 | M37: =SUM(G37:J37) -> 1
A38: 36 | B38: 37 | C38: Shutter Island | D38: 2010 | E38: 18+ | F38: 88/100 | G38: 1 | H38: 0 | I38: 0 | J38: 0 | K38: 0 | L38: =IFERROR(VALUE(LEFT(F38,FIND("/",F38)-1))/10,"") -> 8.8 | M38: =SUM(G38:J38) -> 1
A39: 37 | B39: 38 | C39: Always Be My Maybe | D39: 2019 | E39: 13+ | F39: 88/100 | G39: 1 | H39: 0 | I39: 0 | J39: 0 | K39: 0 | L39: =IFERROR(VALUE(LEFT(F39,FIND("/",F39)-1))/10,"") -> 8.8 | M39: =SUM(G39:J39) -> 1
A40: 38 | B40: 39 | C40: The Intouchables | D40: 2011 | E40: 7+ | F40: 88/100 | G40: 1 | H40: 0 | I40: 0 | J40: 0 | K40: 0 | L40: =IFERROR(VALUE(LEFT(F40,FIND("/",F40)-1))/10,"") -> 8.8 | M40: =SUM(G40:J40) -> 1
A41: 39 | B41: 40 | C41: Bill Burr: Paper Tiger | D41: 2019 | E41: 18+ | F41: 87/100 | G41: 1 | H41: 0 | I41: 0 | J41: 0 | K41: 0 | L41: =IFERROR(VALUE(LEFT(F41,FIND("/",F41)-1))/10,"") -> 8.7 | M41: =SUM(G41:J41) -> 1
A42: 40 | B42: 41 | C42: Special 26 | D42: 2013 | F42: 87/100 | G42: 1 | H42: 0 | I42: 0 | J42: 0 | K42: 0 | L42: =IFERROR(VALUE(LEFT(F42,FIND("/",F42)-1))/10,"") -> 8.7 | M42: =SUM(G42:J42) -> 1
A43: 41 | B43: 42 | C43: Kiss the Ground | D43: 2020 | E43: 18+ | F43: 87/100 | G43: 1 | H43: 0 | I43: 0 | J43: 0 | K43: 0 | L43: =IFERROR(VALUE(LEFT(F43,FIND("/",F43)-1))/10,"") -> 8.7 | M43: =SUM(G43:J43) -> 1
A44: 42 | B44: 43 | C44: Crip Camp: A Disability Revolution | D44: 2020 | E44: 18+ | F44: 87/100 | G44: 1 | H44: 0 | I44: 0 | J44: 0 | K44: 0 | L44: =IFERROR(VALUE(LEFT(F44,FIND("/",F44)-1))/10,"") -> 8.7 | M44: =SUM(G44:J44) -> 1
A45: 43 | B45: 44 | C45: Extraction | D45: 2020 | E45: 18+ | F45: 87/100 | G45: 1 | H45: 0 | I45: 0 | J45: 0 | K45: 0 | L45: =IFERROR(VALUE(LEFT(F45,FIND("/",F45)-1))/10,"") -> 8.7 | M45: =SUM(G45:J45) -> 1
A46: 44 | B46: 45 | C46: No Direction Home: Bob Dylan | D46: 2005 | E46: all | F46: 87/100 | G46: 1 | H46: 0 | I46: 0 | J46: 0 | K46: 0 | L46: =IFERROR(VALUE(LEFT(F46,FIND("/",F46)-1))/10,"") -> 8.7 | M46: =SUM(G46:J46) -> 1
A47: 45 | B47: 46 | C47: Kabhi Khushi Kabhie Gham | D47: 2001 | E47: all | F47: 87/100 | G47: 1 | H47: 0 | I47: 0 | J47: 0 | K47: 0 | L47: =IFERROR(VALUE(LEFT(F47,FIND("/",F47)-1))/10,"") -> 8.7 | M47: =SUM(G47:J47) -> 1
A48: 46 | B48: 47 | C48: His House | D48: 2020 | E48: 16+ | F48: 87/100 | G48: 1 | H48: 0 | I48: 0 | J48: 0 | K48: 0 | L48: =IFERROR(VALUE(LEFT(F48,FIND("/",F48)-1))/10,"") -> 8.7 | M48: =SUM(G48:J48) -> 1
A49: 47 | B49: 48 | C49: Super Deluxe | D49: 2019 | E49: 18+ | F49: 87/100 | G49: 1 | H49: 0 | I49: 0 | J49: 0 | K49: 0 | L49: =IFERROR(VALUE(LEFT(F49,FIND("/",F49)-1))/10,"") -> 8.7 | M49: =SUM(G49:J49) -> 1
A50: 48 | B50: 49 | C50: The Guernsey Literary & Potato Peel Pie Society | D50: 2018 | E50: 16+ | F50: 87/100 | G50: 1 | H50: 0 | I50: 0 | J50: 0 | K50: 0 | L50: =IFERROR(VALUE(LEFT(F50,FIND("/",F50)-1))/10,"") -> 8.7 | M50: =SUM(G50:J50) -> 1
A51: 49 | B51: 50 | C51: A Secret Love | D51: 2020 | E51: 18+ | F51: 87/100 | G51: 1 | H51: 0 | I51: 0 | J51: 0 | K51: 0 | L51: =IFERROR(VALUE(LEFT(F51,FIND("/",F51)-1))/10,"") -> 8.7 | M51: =SUM(G51:J51) -> 1
A52: 50 | B52: 51 | C52: The Night Comes for Us | D52: 2018 | E52: 18+ | F52: 87/100 | G52: 1 | H52: 0 | I52: 0 | J52: 0 | K52: 0 | L52: =IFERROR(VALUE(LEFT(F52,FIND("/",F52)-1))/10,"") -> 8.7 | M52: =SUM(G52:J52) -> 1
A53: 51 | B53: 52 | C53: The Big Lebowski | D53: 1998 | E53: 18+ | F53: 87/100 | G53: 1 | H53: 0 | I53: 0 | J53: 0 | K53: 0 | L53: =IFERROR(VALUE(LEFT(F53,FIND("/",F53)-1))/10,"") -> 8.7 | M53: =SUM(G53:J53) -> 1
A54: 52 | B54: 53 | C54: Pad Man | D54: 2018 | E54: 13+ | F54: 87/100 | G54: 1 | H54: 0 | I54: 0 | J54: 0 | K54: 0 | L54: =IFERROR(VALUE(LEFT(F54,FIND("/",F54)-1))/10,"") -> 8.7 | M54: =SUM(G54:J54) -> 1
... A58: 56 | B58: 57 | C58: 3 Idiots | D58: 2009 | E58: 13+ | F58: 86/100 | G58: 1 | H58: 0 | I58: 0 | J58: 0 | K58: 0 | L58: =IFERROR(VALUE(LEFT(F58,FIND("/",F58)-1))/10,"") -> 8.6 | M58: =SUM(G58:J58) -> 1
A59: 57 | B59: 58 | C59: The Distinguished Citizen | D59: 2016 | F59: 86/100 | G59: 1 | H59: 0 | I59: 0 | J59: 0 | K59: 0 | L59: =IFERROR(VALUE(LEFT(F59,FIND("/",F59)-1))/10,"") -> 8.6 | M59: =SUM(G59:J59) -> 1
A60: 58 | B60: 59 | C60: A Shaun the Sheep Movie: Farmageddon | D60: 2019 | E60: all | F60: 86/100 | G60: 1 | H60: 0 | I60: 0 | J60: 0 | K60: 0 | L60: =IFERROR(VALUE(LEFT(F60,FIND("/",F60)-1))/10,"") -> 8.6 | M60: =SUM(G60:J60) -> 1
A61: 59 | B61: 60 | C61: A Clockwork Orange | D61: 1971 | E61: 18+ | F61: 86/100 | G61: 1 | H61: 0 | I61: 0 | J61: 0 | K61: 0 | L61: =IFERROR(VALUE(LEFT(F61,FIND("/",F61)-1))/10,"") -> 8.6 | M61: =SUM(G61:J61) -> 1
A62: 60 | B62: 61 | C62: What Happened to Monday | D62: 2017 | E62: 18+ | F62: 86/100 | G62: 1 | H62: 0 | I62: 0 | J62: 0 | K62: 0 | L62: =IFERROR(VALUE(LEFT(F62,FIND("/",F62)-1))/10,"") -> 8.6 | M62: =SUM(G62:J62) -> 1
A63: 61 | B63: 62 | C63: Anthony Jeselnik: Thoughts and Prayers | D63: 2015 | E63: 18+ | F63: 86/100 | G63: 1 | H63: 0 | I63: 0 | J63: 0 | K63: 0 | L63: =IFERROR(VALUE(LEFT(F63,FIND("/",F63)-1))/10,"") -> 8.6 | M63: =SUM(G63:J63) -> 1
A64: 62 | B64: 63 | C64: The White Helmets | D64: 2016 | E64: 16+ | F64: 86/100 | G64: 1 | H64: 0 | I64: 0 | J64: 0 | K64: 0 | L64: =IFERROR(VALUE(LEFT(F64,FIND("/",F64)-1))/10,"") -> 8.6 | M64: =SUM(G64:J64) -> 1
A65: 63 | B65: 64 | C65: Invader ZIM: Enter the Florpus | D65: 2019 | E65: 7+ | F65: 86/100 | G65: 1 | H65: 0 | I65: 0 | J65: 0 | K65: 0 | L65: =IFERROR(VALUE(LEFT(F65,FIND("/",F65)-1))/10,"") -> 8.6 | M65: =SUM(G65:J65) -> 1
A66: 64 | B66: 65 | C66: Happy as Lazzaro | D66: 2018 | E66: 13+ | F66: 85/100 | G66: 1 | H66: 0 | I66: 0 | J66: 0 | K66: 0 | L66: =IFERROR(VALUE(LEFT(F66,FIND("/",F66)-1))/10,"") -> 8.5 | M66: =SUM(G66:J66) -> 1
A67: 65 | B67: 66 | C67: Chasing Coral | D67: 2017 | F67: 85/100 | G67: 1 | H67: 0 | I67: 0 | J67: 0 | K67: 0 | L67: =IFERROR(VALUE(LEFT(F67,FIND("/",F67)-1))/10,"") -> 8.5 | M67: =SUM(G67:J67) -> 1
A68: 66 | B68: 67 | C68: Kal Ho Naa Ho | D68: 2003 | E68: all | F68: 85/100 | G68: 1 | H68: 0 | I68: 0 | J68: 0 | K68: 0 | L68: =IFERROR(VALUE(LEFT(F68,FIND("/",F68)-1))/10,"") -> 8.5 | M68: =SUM(G68:J68) -> 1
A69: 67 | B69: 68 | C69: Pan's Labyrinth | D69: 2006 | E69: 18+ | F69: 85/100 | G69: 1 | H69: 0 | I69: 0 | J69: 0 | K69: 0 | L69: =IFERROR(VALUE(LEFT(F69,FIND("/",F69)-1))/10,"") -> 8.5 | M69: =SUM(G69:J69) -> 1
A70: 68 | B70: 69 | C70: Team Foxcatcher | D70: 2016 | E70: 16+ | F70: 85/100 | G70: 1 | H70: 0 | I70: 0 | J70: 0 | K70: 0 | L70: =IFERROR(VALUE(LEFT(F70,FIND("/",F70)-1))/10,"") -> 8.5 | M70: =SUM(G70:J70) -> 1
A71: 69 | B71: 70 | C71: The Meyerowitz Stories (New and Selected) | D71: 2017 | E71: 18+ | F71: 85/100 | G71: 1 | H71: 0 | I71: 0 | J71: 0 | K71: 0 | L71: =IFERROR(VALUE(LEFT(F71,FIND("/",F71)-1))/10,"") -> 8.5 | M71: =SUM(G71:J71) -> 1
A72: 70 | B72: 71 | C72: Casino Royale | D72: 2006 | E72: 13+ | F72: 85/100 | G72: 1 | H72: 0 | I72: 0 | J72: 0 | K72: 0 | L72: =IFERROR(VALUE(LEFT(F72,FIND("/",F72)-1))/10,"") -> 8.5 | M72: =SUM(G72:J72) -> 1
A73: 71 | B73: 72 | C73: The Hateful Eight | D73: 2015 | E73: 18+ | F73: 85/100 | G73: 1 | H73: 0 | I73: 0 | J73: 0 | K73: 0 | L73: =IFERROR(VALUE(LEFT(F73,FIND("/",F73)-1))/10,"") -> 8.5 | M73: =SUM(G73:J73) -> 1
A74: 72 | B74: 73 | C74: Rush | D74: 2013 | E74: 18+ | F74: 84/100 | G74: 1 | H74: 0 | I74: 0 | J74: 0 | K74: 0 | L74: =IFERROR(VALUE(LEFT(F74,FIND("/",F74)-1))/10,"") -> 8.4 | M74: =SUM(G74:J74) -> 1
A75: 73 | B75: 74 | C75: Zombieland | D75: 2009 | E75: 18+ | F75: 84/100 | G75: 1 | H75: 0 | I75: 0 | J75: 0 | K75: 0 | L75: =IFERROR(VALUE(LEFT(F75,FIND("/",F75)-1))/10,"") -> 8.4 | M75: =SUM(G75:J75) -> 1
A76: 74 | B76: 75 | C76: Eurovision Song Contest: The Story of Fire Saga | D76: 2020 | E76: 13+ | F76: 84/100 | G76: 1 | H76: 0 | I76: 0 | J76: 0 | K76: 0 | L76: =IFERROR(VALUE(LEFT(F76,FIND("/",F76)-1))/10,"") -> 8.4 | M76: =SUM(G76:J76) -> 1
A77: 75 | B77: 76 | C77: Kapoor & Sons | D77: 2016 | E77: 13+ | F77: 84/100 | G77: 1 | H77: 0 | I77: 0 | J77: 0 | K77: 0 | L77: =IFERROR(VALUE(LEFT(F77,FIND("/",F77)-1))/10,"") -> 8.4 | M77: =SUM(G77:J77) -> 1
A78: 76 | B78: 77 | C78: The Perfection | D78: 2018 | E78: 18+ | F78: 84/100 | G78: 1 | H78: 0 | I78: 0 | J78: 0 | K78: 0 | L78: =IFERROR(VALUE(LEFT(F78,FIND("/",F78)-1))/10,"") -> 8.4 | M78: =SUM(G78:J78) -> 1
A79: 77 | B79: 78 | C79: Dave Chappelle: Sticks & Stones | D79: 2019 | E79: 18+ | F79: 84/100 | G79: 1 | H79: 0 | I79: 0 | J79: 0 | K79: 0 | L79: =IFERROR(VALUE(LEFT(F79,FIND("/",F79)-1))/10,"") -> 8.4 | M79: =SUM(G79:J79) -> 1
... A89: 87 | B89: 88 | C89: Over the Moon | D89: 2020 | E89: 7+ | F89: 84/100 | G89: 1 | H89: 0 | I89: 0 | J89: 0 | K89: 0 | L89: =IFERROR(VALUE(LEFT(F89,FIND("/",F89)-1))/10,"") -> 8.4 | M89: =SUM(G89:J89) -> 1
A90: 88 | B90: 89 | C90: What Happened, Miss Simone? | D90: 2015 | F90: 84/100 | G90: 1 | H90: 0 | I90: 0 | J90: 0 | K90: 0 | L90: =IFERROR(VALUE(LEFT(F90,FIND("/",F90)-1))/10,"") -> 8.4 | M90: =SUM(G90:J90) -> 1
A91: 89 | B91: 90 | C91: Nightcrawler | D91: 2014 | E91: 18+ | F91: 84/100 | G91: 1 | H91: 0 | I91: 0 | J91: 0 | K91: 0 | L91: =IFERROR(VALUE(LEFT(F91,FIND("/",F91)-1))/10,"") -> 8.4 | M91: =SUM(G91:J91) -> 1
A92: 90 | B92: 91 | C92: 1922 | D92: 2017 | E92: 18+ | F92: 84/100 | G92: 1 | H92: 0 | I92: 0 | J92: 0 | K92: 0 | L92: =IFERROR(VALUE(LEFT(F92,FIND("/",F92)-1))/10,"") -> 8.4 | M92: =SUM(G92:J92) -> 1
A93: 91 | B93: 92 | C93: Paddleton | D93: 2019 | E93: 18+ | F93: 84/100 | G93: 1 | H93: 0 | I93: 0 | J93: 0 | K93: 0 | L93: =IFERROR(VALUE(LEFT(F93,FIND("/",F93)-1))/10,"") -> 8.4 | M93: =SUM(G93:J93) -> 1
A94: 92 | B94: 93 | C94: Cargo | D94: 2017 | F94: 84/100 | G94: 1 | H94: 0 | I94: 0 | J94: 0 | K94: 0 | L94: =IFERROR(VALUE(LEFT(F94,FIND("/",F94)-1))/10,"") -> 8.4 | M94: =SUM(G94:J94) -> 1
A95: 93 | B95: 94 | C95: Rain Man | D95: 1988 | E95: 18+ | F95: 83/100 | G95: 1 | H95: 0 | I95: 0 | J95: 0 | K95: 0 | L95: =IFERROR(VALUE(LEFT(F95,FIND("/",F95)-1))/10,"") -> 8.3 | M95: =SUM(G95:J95) -> 1
A96: 94 | B96: 95 | C96: Cuba and the Cameraman | D96: 2017 | F96: 83/100 | G96: 1 | H96: 0 | I96: 0 | J96: 0 | K96: 0 | L96: =IFERROR(VALUE(LEFT(F96,FIND("/",F96)-1))/10,"") -> 8.3 | M96: =SUM(G96:J96) -> 1
A97: 95 | B97: 96 | C97: The Ritual | D97: 2017 | E97: 18+ | F97: 83/100 | G97: 1 | H97: 0 | I97: 0 | J97: 0 | K97: 0 | L97: =IFERROR(VALUE(LEFT(F97,FIND("/",F97)-1))/10,"") -> 8.3 | M97: =SUM(G97:J97) -> 1
A98: 96 | B98: 97 | C98: The Hater | D98: 2020 | E98: 18+ | F98: 83/100 | G98: 1 | H98: 0 | I98: 0 | J98: 0 | K98: 0 | L98: =IFERROR(VALUE(LEFT(F98,FIND("/",F98)-1))/10,"") -> 8.3 | M98: =SUM(G98:J98) -> 1
A99: 97 | B99: 98 | C99: The Edge of Democracy | D99: 2019 | E99: 16+ | F99: 83/100 | G99: 1 | H99: 0 | I99: 0 | J99: 0 | K99: 0 | L99: =IFERROR(VALUE(LEFT(F99,FIND("/",F99)-1))/10,"") -> 8.3 | M99: =SUM(G99:J99) -> 1
A100: 98 | B100: 99 | C100: 46225 | D100: 2018 | E100: 18+ | F100: 83/100 | G100: 1 | H100: 0 | I100: 0 | J100: 0 | K100: 0 | L100: =IFERROR(VALUE(LEFT(F100,FIND("/",F100)-1))/10,"") -> 8.3 | M100: =SUM(G100:J100) -> 1
A101: 99 | B101: 100 | C101: Adam Sandler: 100% Fresh | D101: 2018 | E101: 18+ | F101: 83/100 | G101: 1 | H101: 0 | I101: 0 | J101: 0 | K101: 0 | L101: =IFERROR(VALUE(LEFT(F101,FIND("/",F101)-1))/10,"") -> 8.3 | M101: =SUM(G101:J101) -> 1
A102: 100 | B102: 101 | C102: Guru | D102: 2007 | E102: 13+ | F102: 83/100 | G102: 1 | H102: 0 | I102: 0 | J102: 0 | K102: 0 | L102: =IFERROR(VALUE(LEFT(F102,FIND("/",F102)-1))/10,"") -> 8.3 | M102: =SUM(G102:J102) -> 1
A103: 101 | B103: 102 | C103: A Twelve-Year Night | D103: 2018 | E103: 18+ | F103: 83/100 | G103: 1 | H103: 0 | I103: 0 | J103: 0 | K103: 0 | L103: =IFERROR(VALUE(LEFT(F103,FIND("/",F103)-1))/10,"") -> 8.3 | M103: =SUM(G103:J103) -> 1
A104: 102 | B104: 103 | C104: Dumplin' | D104: 2018 | E104: 13+ | F104: 83/100 | G104: 1 | H104: 0 | I104: 0 | J104: 0 | K104: 0 | L104: =IFERROR(VALUE(LEFT(F104,FIND("/",F104)-1))/10,"") -> 8.3 | M104: =SUM(G104:J104) -> 1
A105: 103 | B105: 104 | C105: The Conjuring | D105: 2013 | E105: 18+ | F105: 83/100 | G105: 1 | H105: 0 | I105: 0 | J105: 0 | K105: 0 | L105: =IFERROR(VALUE(LEFT(F105,FIND("/",F105)-1))/10,"") -> 8.3 | M105: =SUM(G105:J105) -> 1
A106: 104 | B106: 105 | C106: Marriage Story | D106: 2019 | E106: 18+ | F106: 83/100 | G106: 1 | H106: 0 | I106: 0 | J106: 0 | K106: 0 | L106: =IFERROR(VALUE(LEFT(F106,FIND("/",F106)-1))/10,"") -> 8.3 | M106: =SUM(G106:J106) -> 1
A107: 105 | B107: 106 | C107: My Octopus Teacher | D107: 2020 | E107: all | F107: 83/100 | G107: 1 | H107: 0 | I107: 0 | J107: 0 | K107: 0 | L107: =IFERROR(VALUE(LEFT(F107,FIND("/",F107)-1))/10,"") -> 8.3 | M107: =SUM(G107:J107) -> 1
A108: 106 | B108: 107 | C108: About Time | D108: 2013 | E108: 13+ | F108: 83/100 | G108: 1 | H108: 0 | I108: 0 | J108: 0 | K108: 0 | L108: =IFERROR(VALUE(LEFT(F108,FIND("/",F108)-1))/10,"") -> 8.3 | M108: =SUM(G108:J108) -> 1
A109: 107 | B109: 108 | C109: Hey Arnold! The Jungle Movie | D109: 2017 | E109: 7+ | F109: 83/100 | G109: 1 | H109: 1 | I109: 0 | J109: 0 | K109: 0 | L109: =IFERROR(VALUE(LEFT(F109,FIND("/",F109)-1))/10,"") -> 8.3 | M109: =SUM(G109:J109) -> 2
A110: 108 | B110: 109 | C110: Kung Fu Panda | D110: 2008 | E110: 7+ | F110: 83/100 | G110: 1 | H110: 0 | I110: 0 | J110: 0 | K110: 0 | L110: =IFERROR(VALUE(LEFT(F110,FIND("/",F110)-1))/10,"") -> 8.3 | M110: =SUM(G110:J110) -> 1
A111: 109 | B111: 110 | C111: Superbad | D111: 2007 | E111: 18+ | F111: 83/100 | G111: 1 | H111: 0 | I111: 0 | J111: 0 | K111: 0 | L111: =IFERROR(VALUE(LEFT(F111,FIND("/",F111)-1))/10,"") -> 8.3 | M111: =SUM(G111:J111) -> 1
A112: 110 | B112: 111 | C112: The Invisible Guest | D112: 2016 | E112: 18+ | F112: 83/100 | G112: 1 | H112: 0 | I112: 0 | J112: 0 | K112: 0 | L112: =IFERROR(VALUE(LEFT(F112,FIND("/",F112)-1))/10,"") -> 8.3 | M112: =SUM(G112:J112) -> 1
... A115: 113 | B115: 114 | C115: The Theory of Everything | D115: 2014 | E115: 13+ | F115: 82/100 | G115: 1 | H115: 0 | I115: 0 | J115: 0 | K115: 0 | L115: =IFERROR(VALUE(LEFT(F115,FIND("/",F115)-1))/10,"") -> 8.2 | M115: =SUM(G115:J115) -> 1
A116: 114 | B116: 115 | C116: Springsteen On Broadway | D116: 2018 | F116: 82/100 | G116: 1 | H116: 0 | I116: 0 | J116: 0 | K116: 0 | L116: =IFERROR(VALUE(LEFT(F116,FIND("/",F116)-1))/10,"") -> 8.2 | M116: =SUM(G116:J116) -> 1
A117: 115 | B117: 116 | C117: The Life Ahead | D117: 2020 | E117: 13+ | F117: 82/100 | G117: 1 | H117: 0 | I117: 0 | J117: 0 | K117: 0 | L117: =IFERROR(VALUE(LEFT(F117,FIND("/",F117)-1))/10,"") -> 8.2 | M117: =SUM(G117:J117) -> 1
A118: 116 | B118: 117 | C118: The Terminal | D118: 2004 | E118: 13+ | F118: 82/100 | G118: 1 | H118: 0 | I118: 1 | J118: 0 | K118: 0 | L118: =IFERROR(VALUE(LEFT(F118,FIND("/",F118)-1))/10,"") -> 8.2 | M118: =SUM(G118:J118) -> 2
A119: 117 | B119: 118 | C119: Scott Pilgrim vs. the World | D119: 2010 | E119: 13+ | F119: 82/100 | G119: 1 | H119: 0 | I119: 0 | J119: 0 | K119: 0 | L119: =IFERROR(VALUE(LEFT(F119,FIND("/",F119)-1))/10,"") -> 8.2 | M119: =SUM(G119:J119) -> 1
A120: 118 | B120: 119 | C120: Being Elmo: A Puppeteer's Journey | D120: 2011 | E120: 7+ | F120: 82/100 | G120: 1 | H120: 0 | I120: 0 | J120: 0 | K120: 0 | L120: =IFERROR(VALUE(LEFT(F120,FIND("/",F120)-1))/10,"") -> 8.2 | M120: =SUM(G120:J120) -> 1
A121: 119 | B121: 120 | C121: Life of Brian | D121: 1979 | E121: 18+ | F121: 82/100 | G121: 1 | H121: 0 | I121: 0 | J121: 0 | K121: 0 | L121: =IFERROR(VALUE(LEFT(F121,FIND("/",F121)-1))/10,"") -> 8.2 | M121: =SUM(G121:J121) -> 1
A122: 120 | B122: 121 | C122: The Resistance Banker | D122: 2018 | E122: 18+ | F122: 82/100 | G122: 1 | H122: 0 | I122: 0 | J122: 0 | K122: 0 | L122: =IFERROR(VALUE(LEFT(F122,FIND("/",F122)-1))/10,"") -> 8.2 | M122: =SUM(G122:J122) -> 1
A123: 121 | B123: 122 | C123: How to Train Your Dragon 2 | D123: 2014 | E123: 7+ | F123: 82/100 | G123: 1 | H123: 0 | I123: 0 | J123: 0 | K123: 0 | L123: =IFERROR(VALUE(LEFT(F123,FIND("/",F123)-1))/10,"") -> 8.2 | M123: =SUM(G123:J123) -> 1
A124: 122 | B124: 123 | C124: The Endless Trench | D124: 2019 | F124: 82/100 | G124: 1 | H124: 0 | I124: 0 | J124: 0 | K124: 0 | L124: =IFERROR(VALUE(LEFT(F124,FIND("/",F124)-1))/10,"") -> 8.2 | M124: =SUM(G124:J124) -> 1
A125: 123 | B125: 124 | C125: Even the Rain | D125: 2010 | F125: 82/100 | G125: 1 | H125: 0 | I125: 0 | J125: 0 | K125: 0 | L125: =IFERROR(VALUE(LEFT(F125,FIND("/",F125)-1))/10,"") -> 8.2 | M125: =SUM(G125:J125) -> 1
A126: 124 | B126: 125 | C126: Love Actually | D126: 2003 | E126: 18+ | F126: 82/100 | G126: 1 | H126: 0 | I126: 0 | J126: 0 | K126: 0 | L126: =IFERROR(VALUE(LEFT(F126,FIND("/",F126)-1))/10,"") -> 8.2 | M126: =SUM(G126:J126) -> 1
A127: 125 | B127: 126 | C127: Dear Ex | D127: 2018 | E127: 18+ | F127: 82/100 | G127: 1 | H127: 0 | I127: 0 | J127: 0 | K127: 0 | L127: =IFERROR(VALUE(LEFT(F127,FIND("/",F127)-1))/10,"") -> 8.2 | M127: =SUM(G127:J127) -> 1
A128: 126 | B128: 127 | C128: Braven | D128: 2018 | E128: 18+ | F128: 82/100 | G128: 1 | H128: 0 | I128: 0 | J128: 0 | K128: 0 | L128: =IFERROR(VALUE(LEFT(F128,FIND("/",F128)-1))/10,"") -> 8.2 | M128: =SUM(G128:J128) -> 1
A129: 127 | B129: 128 | C129: Period. End of Sentence. | D129: 2018 | F129: 82/100 | G129: 1 | H129: 0 | I129: 0 | J129: 0 | K129: 0 | L129: =IFERROR(VALUE(LEFT(F129,FIND("/",F129)-1))/10,"") -> 8.2 | M129: =SUM(G129:J129) -> 1
A130: 128 | B130: 129 | C130: Captain Fantastic | D130: 2016 | E130: 18+ | F130: 82/100 | G130: 1 | H130: 0 | I130: 0 | J130: 0 | K130: 0 | L130: =IFERROR(VALUE(LEFT(F130,FIND("/",F130)-1))/10,"") -> 8.2 | M130: =SUM(G130:J130) -> 1
A131: 129 | B131: 130 | C131: Veronica | D131: 2017 | E131: 18+ | F131: 81/100 | G131: 1 | H131: 0 | I131: 0 | J131: 0 | K131: 0 | L131: =IFERROR(VALUE(LEFT(F131,FIND("/",F131)-1))/10,"") -> 8.1 | M131: =SUM(G131:J131) -> 1
A132: 130 | B132: 131 | C132: The Siege of Jadotville | D132: 2016 | F132: 81/100 | G132: 1 | H132: 0 | I132: 0 | J132: 0 | K132: 0 | L132: =IFERROR(VALUE(LEFT(F132,FIND("/",F132)-1))/10,"") -> 8.1 | M132: =SUM(G132:J132) -> 1
A133: 131 | B133: 132 | C133: Into the Inferno | D133: 2016 | F133: 81/100 | G133: 1 | H133: 0 | I133: 0 | J133: 0 | K133: 0 | L133: =IFERROR(VALUE(LEFT(F133,FIND("/",F133)-1))/10,"") -> 8.1 | M133: =SUM(G133:J133) -> 1
A134: 132 | B134: 133 | C134: Ricky Gervais: Humanity | D134: 2018 | E134: 18+ | F134: 81/100 | G134: 1 | H134: 0 | I134: 0 | J134: 0 | K134: 0 | L134: =IFERROR(VALUE(LEFT(F134,FIND("/",F134)-1))/10,"") -> 8.1 | M134: =SUM(G134:J134) -> 1
A135: 133 | B135: 134 | C135: A Whisker Away | D135: 2020 | E135: 7+ | F135: 81/100 | G135: 1 | H135: 0 | I135: 0 | J135: 0 | K135: 0 | L135: =IFERROR(VALUE(LEFT(F135,FIND("/",F135)-1))/10,"") -> 8.1 | M135: =SUM(G135:J135) -> 1
A136: 134 | B136: 135 | C136: Lady Bird | D136: 2017 | E136: 18+ | F136: 81/100 | G136: 1 | H136: 0 | I136: 0 | J136: 0 | K136: 0 | L136: =IFERROR(VALUE(LEFT(F136,FIND("/",F136)-1))/10,"") -> 8.1 | M136: =SUM(G136:J136) -> 1
...

Sheet DASHBOARD
A2: OTT MOVIE STREAMING ANALYTICS DASHBOARD
A3: DAV Lab Assignment 2 | Formula-based Excel analysis
A6: 1. Dataset Profile | O6: 7. Movies Released by Year
O7: Years | R7: Movies
A8: Total number of records | D8: =COUNTA(DATA!C2:C9516) -> 9515 | O8: 2019 | R8: {=SUMPRODUCT(--(DATA!D2:D9516&""=A2&""))} -> 0
A9: Total number of columns | D9: =COLUMNS(A1:K1) -> 11 | O9: 2020 | R9: {=SUMPRODUCT(--(DATA!D3:D9517&""=A3&""))} -> 0
A10: Earliest movie year | D10: =_xlfn.MINIFS(DATA!D2:D9516,DATA!D2:D9516,">0") -> 1914 | O10: 2021 | R10: {=SUMPRODUCT(--(DATA!D4:D9518&""=A4&""))} -> 2
A11: Latest movie year | D11: =MAX(DATA!D2:D9516) -> 2021 | O11: 2022 | R11: {=SUMPRODUCT(--(DATA!D5:D9519&""=A5&""))} -> 3
A12: Average movie year | D12: =AVERAGEIFS(DATA!D2:D9516,DATA!D2:D9516,">0") -> 2007.4224 | O12: 2023 | R12: {=SUMPRODUCT(--(DATA!D6:D9520&""=A6&""))} -> 0
A13: Missing Age | D13: =COUNTBLANK(DATA!E2:E9516) -> 4177
A14: Missing Rotten Tomatoes | D14: =COUNTBLANK(DATA!F2:F9516) -> 7
A17: 2. Rotten Tomatoes Score
A19: Average Rating | D19: =AVERAGE(DATA!L2:L9516) -> 5.3545015
A20: Highest Rating | D20: =MAX(DATA!L2:L9516) -> 9.8
A21: Lowest Rating | D21: =MIN(DATA!L2:L9516) -> 1
A22: Movies rated 8+ | D22: =COUNTIF(DATA!L2:L9516,">=8") -> 335
A25: 3. Streaming Platforms
A26: Platforms | D26: Movies
A27: Netflix | D27: =COUNTIF(DATA!G2:G9516,1) -> 3695
A28: Hulu | D28: =COUNTIF(DATA!H2:H9516,1) -> 1047
A29: Prime Video | D29: =COUNTIF(DATA!I2:I9516,1) -> 4113
A30: Disney+ | D30: =COUNTIF(DATA!J2:J9516,1) -> 922
A33: 4. Platform Percentage
A34: Platforms | D34: Percent
A35: Netflix | D35: =COUNTIF(DATA!G2:G9516,1)/COUNTA(DATA!C2:C9516) -> 0.38833421
A36: Hulu | D36: =COUNTIF(DATA!H2:H9516,1)/COUNTA(DATA!C2:C9516) -> 0.11003678
A37: Prime Video | D37: =COUNTIF(DATA!I2:I9516,1)/COUNTA(DATA!C2:C9516) -> 0.43226484
A38: Disney+ | D38: =COUNTIF(DATA!J2:J9516,1)/COUNTA(DATA!C2:C9516) -> 0.096899632
A46: 5. Rating Distribution
A47: Rating | C47: Movies
A48: 0–2 | C48: =COUNTIFS(DATA!L2:L9516,">=0",DATA!L2:L9516,"<2") -> 119
A49: 2–4 | C49: =COUNTIFS(DATA!L2:L9516,">=2",DATA!L2:L9516,"<4") -> 1036
A50: 4–6 | C50: =COUNTIFS(DATA!L2:L9516,">=4",DATA!L2:L9516,"<6") -> 5429
A51: 6–8 | C51: =COUNTIFS(DATA!L2:L9516,">=6",DATA!L2:L9516,"<8") -> 2589
A52: 8–10 | C52: =COUNTIFS(DATA!L2:L9516,">=8",DATA!L2:L9516,"<=10") -> 335
A59: 6. Age Rating
A60: Age | C60: Count
A61: 18+ | C61: =COUNTIF(DATA!E2:E9516,"18+") -> 2276
A62: 16+ | C62: =COUNTIF(DATA!E2:E9516,"16+") -> 276
A63: 13+ | C63: =COUNTIF(DATA!E2:E9516,"13+") -> 998
A64: 7+ | C64: =COUNTIF(DATA!E2:E9516,"7+") -> 1090
A65: all | C65: =COUNTIF(DATA!E2:E9516,"all") -> 698
A66: Blank | C66: =COUNTBLANK(DATA!E2:E9516) -> 4177
A73: 8. Highly Rated Movies by Platform
A74: Platforms | D74: Rating ≥ 8
A75: Netflix | D75: =COUNTIFS(DATA!G2:G9516,1,DATA!L2:L9516,">=8") -> 168
A76: Hulu | D76: =COUNTIFS(DATA!H2:H9516,1,DATA!L2:L9516,">=8") -> 49
A77: Prime Video | D77: =COUNTIFS(DATA!I2:I9516,1,DATA!L2:L9516,">=8") -> 53
A78: Disney+ | D78: =COUNTIFS(DATA!J2:J9516,1,DATA!L2:L9516,">=8") -> 75
A85: 9. Platform Count
A86: Platforms | C86: Movies
A87: 1 | C87: =COUNTIF(DATA!M2:M9516,1) -> 9262
A88: 2 | C88: =COUNTIF(DATA!M2:M9516,2) -> 245
A89: 3 | C89: =COUNTIF(DATA!M2:M9516,3) -> 7
A90: 4 | C90: =COUNTIF(DATA!M2:M9516,4) -> 1
D100: {=IFERROR(SUMPRODUCT((VALUE(DATA!$D$2:$D$9516)=VALUE(A2))*DATA!$L$2:$L$9516)/SUMPRODUCT((VALUE(DATA!$D$2:$D$9516)=VALUE(A2))*(DATA!$L$2:$L$9516>0)),"")}
